{
  "$schema": "https://schema.tauri.app/config/2",
  "productName": "Data Masker",
  "version": "1.0.0",
  "identifier": "com.datamasker.app",
  "build": {
    "beforeDevCommand": "npm run dev",
    "devUrl": "http://localhost:1420",
    "beforeBuildCommand": "npm run build",
    "frontendDist": "../dist"
  },
  "app": {
    "windows": [
      {
        "title": "Data Masker - 文件脱敏工具",
        "width": 1280,
        "height": 800,
        "minWidth": 1024,
        "minHeight": 600,
        "center": true,
        "resizable": true
      }
    ],
    "security": {
      "csp": "default-src 'self'; script-src 'self'; style-src 'self' 'unsafe-inline'; img-src 'self' data:; font-src 'self' data:"
    }
  },
  "bundle": {
    "active": true,
    "targets": "all",
    "icon": [
      "icons/32x32.png",
      "icons/128x128.png",
      "icons/128x128@2x.png",
      "icons/icon.icns",
      "icons/icon.ico"
    ],
    "shortDescription": "文件脱敏工具",
    "longDescription": "安全、高效的本地文件脱敏工具，敏感数据不上传云端",
    "category": "Utility"
  }
}
